cws/__init__.py
cws/__main__.py
cws/config.py
cws/cws.py
cws/searchresponse.py
cws/searchresult.py
cws/provider/__init__.py
cws/provider/google.yml
cws/provider/searchprovider.py
cws/provider/youtube.yml
tests/__init__.py
tests/clitools.py
tests/conftest.py
tests/test_config.py
tests/test_cws.py
tests/test_searchprovider.py
cws_clisearch-0.3.2.dist-info/METADATA
cws_clisearch-0.3.2.dist-info/WHEEL
cws_clisearch-0.3.2.dist-info/entry_points.txt
cws_clisearch-0.3.2.dist-info/top_level.txt
cws_clisearch-0.3.2.dist-info/RECORD
