Metadata-Version: 2.1
Name: cws-clisearch
Version: 0.3.2
Summary: A CLI web search tool.
Home-page: https://github.com/jwizzle/cws
Author: j wizzle
Author-email: info@hossel.net
License: UNKNOWN
Platform: UNKNOWN
Classifier: Programming Language :: Python :: 3
Classifier: License :: OSI Approved :: MIT License
Classifier: Operating System :: OS Independent
Requires-Python: >=3.7
Requires-Dist: requests
Requires-Dist: pyyaml
